setup.cfg
setup.py
homework_exercise/__init__.py
homework_exercise/_calculation.py
homework_exercise/_data.py
homework_exercise.egg-info/PKG-INFO
homework_exercise.egg-info/SOURCES.txt
homework_exercise.egg-info/dependency_links.txt
homework_exercise.egg-info/requires.txt
homework_exercise.egg-info/top_level.txt