Metadata-Version: 2.1
Name: homework-exercise
Version: 0.0.1
Summary: Sample package as homework.
Home-page: UNKNOWN
Author: Author
Author-email: Author@gmail.com
License: BSD-3-Clause
Platform: UNKNOWN
